uneval/__init__.py
uneval/astbuild.py
uneval/dsl.py
uneval/evaluation.py
uneval/expression.py
uneval/lambdas.py
uneval/scopedexpression.py
uneval-0.2.0.dist-info/licenses/LICENSE
uneval-0.2.0.dist-info/METADATA
uneval-0.2.0.dist-info/WHEEL
uneval-0.2.0.dist-info/top_level.txt
uneval-0.2.0.dist-info/RECORD
