Metadata-Version: 2.4
Name: uneval
Version: 0.2.0
Summary: Library for generating python-expressions
Author-email: lverweijen <lauwerund@gmail.com>
License: Apache License 2.0
Project-URL: Homepage, https://github.com/lverweijen/python-uneval
Project-URL: Repository, https://github.com/lverweijen/python-uneval
Project-URL: Issues, https://github.com/lverweijen/python-uneval/issues
Project-URL: Changelog, https://github.com/lverweijen/python-uneval/blob/main/changes.md
Project-URL: Pypi, https://github.com/lverweijen/python-uneval
Keywords: expression,ast,dsl,fexpr,lambda,symbolic
Classifier: Intended Audience :: Developers
Classifier: Operating System :: OS Independent
Classifier: License :: OSI Approved :: Apache Software License
Classifier: Programming Language :: Python :: 3
Classifier: Programming Language :: Python :: 3.10
Classifier: Programming Language :: Python :: 3.11
Classifier: Programming Language :: Python :: 3.12
Classifier: Programming Language :: Python :: 3.13
Classifier: Programming Language :: Python :: 3.14
Classifier: Topic :: Software Development :: Code Generators
Classifier: Typing :: Typed
Requires-Python: >=3.10
License-File: LICENSE
Dynamic: license-file
